upd8/__init__.py
upd8/_change.py
upd8/_decorator.py
upd8/_exception.py
upd8/_field.py
upd8/_versioned.py
upd8-0.0.2.dist-info/licenses/LICENSE.md
upd8-0.0.2.dist-info/WHEEL
upd8-0.0.2.dist-info/METADATA
upd8-0.0.2.dist-info/RECORD
