Metadata-Version: 2.4
Name: upd8
Version: 0.0.2
Summary: track updates to python objects
Author-email: Gareth Davidson <gaz@bitplane.net>
License-File: LICENSE.md
Requires-Dist: flake8 ; extra == "dev"
Requires-Dist: pre-commit ; extra == "dev"
Requires-Dist: pytest ; extra == "dev"
Requires-Dist: coverage ; extra == "dev"
Requires-Dist: pytest-cov ; extra == "dev"
Requires-Dist: pytest-asyncio ; extra == "dev"
Requires-Dist: build ; extra == "dev"
Requires-Dist: twine ; extra == "dev"
Provides-Extra: dev
